citext/__init__.py
tests/__init__.py
tests/test_citext.py
sqlalchemy_citext-1.6.3.dist-info/LICENSE
sqlalchemy_citext-1.6.3.dist-info/METADATA
sqlalchemy_citext-1.6.3.dist-info/WHEEL
sqlalchemy_citext-1.6.3.dist-info/top_level.txt
sqlalchemy_citext-1.6.3.dist-info/RECORD
