Metadata-Version: 2.1
Name: sqlalchemy-citext
Version: 1.6.3
Summary: A sqlalchemy plugin that allows postgres use of CITEXT.
Home-page: https://github.com/mahmoudimus/sqlalchemy-citext
Author: Mahmoud Abdelkader, Davide Setti
Author-email: UNKNOWN
License: BSD
Platform: UNKNOWN
Classifier: Intended Audience :: Developers
Classifier: License :: OSI Approved :: BSD License
Classifier: Programming Language :: Python
Classifier: Programming Language :: Python :: 3
Classifier: Programming Language :: Python :: 2
Classifier: Topic :: Software Development :: Libraries :: Python Modules
Requires-Dist: SQLAlchemy (>=0.6)
